[
  {
    "line": 1,
    "elements": [
      {
        "line": 4,
        "name": "Verify the calender is selected",
        "description": "",
        "id": "this-is-to-calender-handle-functionality;verify-the-calender-is-selected",
        "type": "scenario",
        "keyword": "Scenario",
        "steps": [
          {
            "result": {
              "duration": 5023946900,
              "status": "passed"
            },
            "line": 5,
            "name": "Launch spring \"\u003cURL\u003e\" application",
            "match": {
              "arguments": [
                {
                  "val": "\u003cURL\u003e",
                  "offset": 15
                }
              ],
              "location": "loginSpring.launch_spring_application(String)"
            },
            "keyword": "Given "
          },
          {
            "result": {
              "duration": 14071017900,
              "status": "passed"
            },
            "line": 6,
            "name": "Select Departure date and Return date",
            "match": {
              "location": "southWest.select_Departure_date_and_Return_date()"
            },
            "keyword": "Then "
          }
        ],
        "tags": [
          {
            "line": 3,
            "name": "@calendar"
          }
        ]
      }
    ],
    "name": "This is to calender handle functionality",
    "description": "",
    "id": "this-is-to-calender-handle-functionality",
    "keyword": "Feature",
    "uri": "southWest.feature"
  }
]